mismatch/AssignGroup.py
mismatch/MTLSuperPoints copy.py
mismatch/MTLSuperPoints.py
mismatch/TNMismatchClustering copy.py
mismatch/TNMismatchClustering.py
mismatch/__init__.py
mismatch/__main__.py
mismatch/adni_reference/__init__.py
mismatch/adni_reference/adni_cluster_centroids.csv
mismatch/adni_reference/adni_model_coefficients.csv
mismatch/adni_reference/adni_residual_sd.csv
mismatch/adni_reference/left_partition_membership.npy
mismatch/adni_reference/right_partition_membership.npy
mismatch/atlas/antsMalfLabeling.nii.gz
mismatch/atlas/tpl-ADNINormalAgingANTs_res-01_atlas-DKT_desc-31_dseg.nii.gz
mismatch-0.1.4.dist-info/METADATA
mismatch-0.1.4.dist-info/WHEEL
mismatch-0.1.4.dist-info/entry_points.txt
mismatch-0.1.4.dist-info/licenses/LICENSE
mismatch-0.1.4.dist-info/RECORD
