Metadata-Version: 2.4
Name: mismatch
Version: 0.1.4
Summary: Mismatch clustering for tau and neurodegeneration residuals in Alzheimer's Disease
Project-URL: Homepage, https://github.com/xueying-lyu/mismatch
Project-URL: Repository, https://github.com/xueying-lyu/mismatch
Project-URL: Issues, https://github.com/xueying-lyu/mismatch/issues
Author-email: Xueying Lyu <xylyu@seas.upenn.edu>
License: MIT License
License-File: LICENSE
Classifier: Development Status :: 4 - Beta
Classifier: Intended Audience :: Science/Research
Classifier: License :: OSI Approved :: MIT License
Classifier: Operating System :: OS Independent
Classifier: Programming Language :: Python :: 3
Classifier: Topic :: Scientific/Engineering :: Medical Science Apps.
Requires-Python: >=3.8
Requires-Dist: matplotlib
Requires-Dist: nibabel
Requires-Dist: nilearn
Requires-Dist: numpy
Requires-Dist: pandas
Requires-Dist: pymetis
Requires-Dist: scikit-learn
Requires-Dist: scipy
Requires-Dist: seaborn
Requires-Dist: statsmodels
Requires-Dist: vtk
